notionizer/__init__.py
notionizer/enum.py
notionizer/exception.py
notionizer/functions.py
notionizer/http_request.py
notionizer/notion.py
notionizer/object_adt.py
notionizer/object_basic.py
notionizer/object_block.py
notionizer/object_database.py
notionizer/object_page.py
notionizer/object_user.py
notionizer/properties_basic.py
notionizer/properties_db.py
notionizer/properties_page.py
notionizer/properties_property.py
notionizer/query.py
notionizer/settings.py
test/__init__.py
test/test_block.py
test/test_notion.py
test/test_notion1.py
test/test_notion_getdatabase.py
test/test_object_database.py
test/test_object_page.py
test/test_objects.py
test/test_query.py
notionizer-0.0.8.dist-info/METADATA
notionizer-0.0.8.dist-info/WHEEL
notionizer-0.0.8.dist-info/top_level.txt
notionizer-0.0.8.dist-info/RECORD
