Metadata-Version: 2.1
Name: notionizer
Version: 0.0.8
Summary: Python wrapper for Notion API
Home-page: https://github.com/kimsg1984/notionizer
Author: SeonGyo Kim
Author-email: kimsg1984@gmail.com
Classifier: Programming Language :: Python :: 3
Classifier: License :: OSI Approved :: MIT License
Classifier: Operating System :: OS Independent
Requires-Python: >=3.6
Requires-Dist: requests
